odoo/addons/product_supplierinfo_import_by_barcode/README.rst
odoo/addons/product_supplierinfo_import_by_barcode/__init__.py
odoo/addons/product_supplierinfo_import_by_barcode/__manifest__.py
odoo/addons/product_supplierinfo_import_by_barcode/i18n/es.po
odoo/addons/product_supplierinfo_import_by_barcode/i18n/it.po
odoo/addons/product_supplierinfo_import_by_barcode/i18n/product_supplierinfo_import_by_barcode.pot
odoo/addons/product_supplierinfo_import_by_barcode/migrations/16.0.2.0.0/pre-migration.py
odoo/addons/product_supplierinfo_import_by_barcode/models/__init__.py
odoo/addons/product_supplierinfo_import_by_barcode/models/product_supplier_info.py
odoo/addons/product_supplierinfo_import_by_barcode/models/product_supplierinfo_import_template.py
odoo/addons/product_supplierinfo_import_by_barcode/models/product_template.py
odoo/addons/product_supplierinfo_import_by_barcode/readme/CONFIGURE.md
odoo/addons/product_supplierinfo_import_by_barcode/readme/CONTRIBUTORS.md
odoo/addons/product_supplierinfo_import_by_barcode/readme/DESCRIPTION.md
odoo/addons/product_supplierinfo_import_by_barcode/readme/ROADMAP.md
odoo/addons/product_supplierinfo_import_by_barcode/readme/USAGE.md
odoo/addons/product_supplierinfo_import_by_barcode/security/ir.model.access.csv
odoo/addons/product_supplierinfo_import_by_barcode/static/description/icon.png
odoo/addons/product_supplierinfo_import_by_barcode/static/description/index.html
odoo/addons/product_supplierinfo_import_by_barcode/tests/__init__.py
odoo/addons/product_supplierinfo_import_by_barcode/tests/test_product_supplierinfo_import_by_barcode.py
odoo/addons/product_supplierinfo_import_by_barcode/tests/test_supplier_drinks_complex_sheet.xlsx
odoo/addons/product_supplierinfo_import_by_barcode/tests/test_supplier_drinks_complex_sheet_updated.xlsx
odoo/addons/product_supplierinfo_import_by_barcode/tests/test_supplier_spanish_drinks.xlsx
odoo/addons/product_supplierinfo_import_by_barcode/views/product_supplierinfo_import_template_views.xml
odoo_addon_product_supplierinfo_import_by_barcode-16.0.3.0.0.2.dist-info/METADATA
odoo_addon_product_supplierinfo_import_by_barcode-16.0.3.0.0.2.dist-info/WHEEL
odoo_addon_product_supplierinfo_import_by_barcode-16.0.3.0.0.2.dist-info/top_level.txt
odoo_addon_product_supplierinfo_import_by_barcode-16.0.3.0.0.2.dist-info/RECORD
